servercore/Modpack.py
servercore/ServerCore.py
servercore/__init__.py
TechnicServerCore-0.3.3.dist-info/RECORD
TechnicServerCore-0.3.3.dist-info/metadata.json
TechnicServerCore-0.3.3.dist-info/METADATA
TechnicServerCore-0.3.3.dist-info/WHEEL
TechnicServerCore-0.3.3.dist-info/DESCRIPTION.rst
TechnicServerCore-0.3.3.dist-info/top_level.txt
TechnicServerCore-0.3.3.dist-info/entry_points.txt
