Metadata-Version: 2.0
Name: TechnicServerCore
Version: 0.3.3
Summary: Custom wrapper that downloads and updates Technic modpacks specifically for servers.
Home-page: http://github.com/GenPage/ServerCore/
Author: Dylan Page
Author-email: genpage@technicpack.net
License: UNKNOWN
Platform: UNKNOWN
Classifier: Development Status :: 4 - Beta
Classifier: Environment :: Console
Classifier: Intended Audience :: System Administrators
Classifier: License :: OSI Approved :: GNU Lesser General Public License v3 or later (LGPLv3+)
Classifier: Operating System :: OS Independent
Classifier: Programming Language :: Python :: 2 :: Only
Classifier: Topic :: Software Development :: Libraries
Classifier: Topic :: Software Development :: User Interfaces
Classifier: Topic :: Terminals
Requires-Dist: progressbar (>=2.2)
